trytond/modules/user_view/__init__.py
trytond/modules/user_view/lang.py
trytond/modules/user_view/lang.xml
trytond/modules/user_view/setup.py
trytond/modules/user_view/tryton.cfg
trytond/modules/user_view/user.py
trytond/modules/user_view/user_view.py
trytond/modules/user_view/user_view.xml
trytond/modules/user_view/locale/es.po
trytond/modules/user_view/view/lang_view_form.xml
trytond/modules/user_view/view/user_form.xml
trytond/modules/user_view/view/user_form_preferences.xml
trytond/modules/user_view/view/user_view_field_form.xml
trytond/modules/user_view/view/user_view_field_list.xml
trytond/modules/user_view/view/user_view_form.xml
trytond/modules/user_view/view/user_view_list.xml
kalenis_user_view-6.0.0.dist-info/LICENSE
kalenis_user_view-6.0.0.dist-info/METADATA
kalenis_user_view-6.0.0.dist-info/WHEEL
kalenis_user_view-6.0.0.dist-info/entry_points.txt
kalenis_user_view-6.0.0.dist-info/top_level.txt
kalenis_user_view-6.0.0.dist-info/RECORD
